tracknado/__init__.py
tracknado/_version.py
tracknado/api.py
tracknado/builder.py
tracknado/cli.py
tracknado/converters.py
tracknado/extractors.py
tracknado/models.py
tracknado/schemas.py
tracknado/validation.py
tracknado/as_files/bigGenePred.as
tracknado/old/cli.py
tracknado/old/grouping.py
tracknado/old/hub_setup.py
tracknado/old/make_hub.py
tracknado/old/track.py
tracknado-0.3.1.dist-info/licenses/LICENSE
tracknado-0.3.1.dist-info/METADATA
tracknado-0.3.1.dist-info/WHEEL
tracknado-0.3.1.dist-info/entry_points.txt
tracknado-0.3.1.dist-info/top_level.txt
tracknado-0.3.1.dist-info/RECORD
