Metadata-Version: 2.4
Name: tracknado
Version: 0.3.1
Summary: CLI library to generate UCSC trackhubs from sequencing data
Author-email: Alastair Smith <alastair.smith@ndcls.ox.ac.uk>
License: GNU GENERAL PUBLIC LICENSE Version 3
Requires-Python: >=3.7
License-File: LICENSE
Requires-Dist: typer
Requires-Dist: pandas
Requires-Dist: cookiecutter
Requires-Dist: setuptools_scm
Requires-Dist: seaborn
Requires-Dist: trackhub
Requires-Dist: Pillow
Requires-Dist: loguru
Requires-Dist: pydantic>=2.0
Requires-Dist: pandera>=0.18
Provides-Extra: docs
Requires-Dist: mkdocs; extra == "docs"
Requires-Dist: mkdocs-material; extra == "docs"
Requires-Dist: mkdocstrings[python]; extra == "docs"
Dynamic: license-file
